[
    {
        "crystal_index": 5,
        "crystal_name": "AgAuO2",
        "Oxy_site_label": "O1",
        "Oxy_site_index": 4,
        "Oxy_vacancy_formation_energy": 2.31297225999999,
        "node_features": [
            [
                47.0,
                5.0,
                11.0,
                0.0,
                0.0,
                1.93,
                2.11,
                1.6,
                7.576234,
                21.4844,
                1.304473,
                128.0,
                0.0,
                -900.324578,
                -129.859807,
                -120.913351,
                -23.678437,
                -20.06763,
                -3.22309,
                -13.367803,
                -2.086602,
                -0.157407,
                -0.298706,
                0.0,
                0.0,
                0.0,
                0.0,
                0.0,
                0.0,
                0.0,
                0.0,
                0.0
            ],
            [
                47.0,
                5.0,
                11.0,
                0.0,
                0.0,
                1.93,
                2.11,
                1.6,
                7.576234,
                21.4844,
                1.304473,
                128.0,
                0.0,
                -900.324578,
                -129.859807,
                -120.913351,
                -23.678437,
                -20.06763,
                -3.22309,
                -13.367803,
                -2.086602,
                -0.157407,
                -0.298706,
                0.0,
                0.0,
                0.0,
                0.0,
                0.0,
                0.0,
                0.0,
                0.0,
                0.0
            ],
            [
                79.0,
                6.0,
                11.0,
                0.0,
                0.0,
                2.54,
                2.14,
                1.35,
                9.225554,
                20.203,
                2.30861025,
                124.0,
                0.0,
                -2683.508245,
                -447.888973,
                -430.725701,
                -104.824516,
                -96.707,
                -22.078357,
                -81.511751,
                -18.578652,
                -3.113936,
                -12.131815,
                -2.002495,
                -0.162334,
                -3.486824,
                -0.304738,
                0.0,
                0.0,
                0.0,
                0.0,
                0.0
            ],
            [
                79.0,
                6.0,
                11.0,
                0.0,
                0.0,
                2.54,
                2.14,
                1.35,
                9.225554,
                20.203,
                2.30861025,
                124.0,
                0.0,
                -2683.508245,
                -447.888973,
                -430.725701,
                -104.824516,
                -96.707,
                -22.078357,
                -81.511751,
                -18.578652,
                -3.113936,
                -12.131815,
                -2.002495,
                -0.162334,
                -3.486824,
                -0.304738,
                0.0,
                0.0,
                0.0,
                0.0,
                0.0
            ],
            [
                8.0,
                2.0,
                16.0,
                0.0,
                0.0,
                3.44,
                1.52,
                0.6,
                13.618055,
                35.12112,
                1.4611053,
                63.0,
                1.0,
                -18.758245,
                -0.871362,
                -0.338381,
                0.0,
                0.0,
                0.0,
                0.0,
                0.0,
                0.0,
                0.0,
                0.0,
                0.0,
                0.0,
                0.0,
                0.0,
                0.0,
                0.0,
                0.0,
                0.0
            ],
            [
                8.0,
                2.0,
                16.0,
                0.0,
                0.0,
                3.44,
                1.52,
                0.6,
                13.618055,
                35.12112,
                1.4611053,
                63.0,
                0.0,
                -18.758245,
                -0.871362,
                -0.338381,
                0.0,
                0.0,
                0.0,
                0.0,
                0.0,
                0.0,
                0.0,
                0.0,
                0.0,
                0.0,
                0.0,
                0.0,
                0.0,
                0.0,
                0.0,
                0.0
            ],
            [
                8.0,
                2.0,
                16.0,
                0.0,
                0.0,
                3.44,
                1.52,
                0.6,
                13.618055,
                35.12112,
                1.4611053,
                63.0,
                0.0,
                -18.758245,
                -0.871362,
                -0.338381,
                0.0,
                0.0,
                0.0,
                0.0,
                0.0,
                0.0,
                0.0,
                0.0,
                0.0,
                0.0,
                0.0,
                0.0,
                0.0,
                0.0,
                0.0,
                0.0
            ],
            [
                8.0,
                2.0,
                16.0,
                0.0,
                0.0,
                3.44,
                1.52,
                0.6,
                13.618055,
                35.12112,
                1.4611053,
                63.0,
                0.0,
                -18.758245,
                -0.871362,
                -0.338381,
                0.0,
                0.0,
                0.0,
                0.0,
                0.0,
                0.0,
                0.0,
                0.0,
                0.0,
                0.0,
                0.0,
                0.0,
                0.0,
                0.0,
                0.0,
                0.0
            ]
        ],
        "edges": [
            [
                0,
                6
            ],
            [
                0,
                4
            ],
            [
                1,
                7
            ],
            [
                1,
                5
            ],
            [
                2,
                4
            ],
            [
                2,
                7
            ],
            [
                2,
                5
            ],
            [
                2,
                6
            ],
            [
                3,
                7
            ],
            [
                3,
                6
            ],
            [
                3,
                4
            ],
            [
                3,
                5
            ],
            [
                4,
                3
            ],
            [
                4,
                2
            ],
            [
                4,
                0
            ],
            [
                5,
                1
            ],
            [
                5,
                2
            ],
            [
                5,
                3
            ],
            [
                6,
                3
            ],
            [
                6,
                0
            ],
            [
                6,
                2
            ],
            [
                7,
                3
            ],
            [
                7,
                2
            ],
            [
                7,
                1
            ]
        ],
        "edge_attr": [
            [
                2.112389096960098,
                0
            ],
            [
                2.112389096960098,
                1
            ],
            [
                2.1123890969600985,
                0
            ],
            [
                2.1123890969600985,
                0
            ],
            [
                2.0041051963278567,
                1
            ],
            [
                2.0067254438278246,
                0
            ],
            [
                2.006725443827824,
                0
            ],
            [
                2.0041051963278567,
                0
            ],
            [
                2.004105196327856,
                0
            ],
            [
                2.0067254438278246,
                0
            ],
            [
                2.0067254438278246,
                1
            ],
            [
                2.0041051963278567,
                0
            ],
            [
                2.0067254438278246,
                1
            ],
            [
                2.0041051963278567,
                1
            ],
            [
                2.112389096960098,
                1
            ],
            [
                2.1123890969600985,
                0
            ],
            [
                2.006725443827824,
                0
            ],
            [
                2.0041051963278567,
                0
            ],
            [
                2.0067254438278246,
                0
            ],
            [
                2.112389096960098,
                0
            ],
            [
                2.0041051963278567,
                0
            ],
            [
                2.004105196327856,
                0
            ],
            [
                2.0067254438278246,
                0
            ],
            [
                2.1123890969600985,
                0
            ]
        ]
    },
    {
        "crystal_index": 5,
        "crystal_name": "AgAuO2",
        "Oxy_site_label": "O1",
        "Oxy_site_index": 5,
        "Oxy_vacancy_formation_energy": 2.31297225999999,
        "node_features": [
            [
                47.0,
                5.0,
                11.0,
                0.0,
                0.0,
                1.93,
                2.11,
                1.6,
                7.576234,
                21.4844,
                1.304473,
                128.0,
                0.0,
                -900.324578,
                -129.859807,
                -120.913351,
                -23.678437,
                -20.06763,
                -3.22309,
                -13.367803,
                -2.086602,
                -0.157407,
                -0.298706,
                0.0,
                0.0,
                0.0,
                0.0,
                0.0,
                0.0,
                0.0,
                0.0,
                0.0
            ],
            [
                47.0,
                5.0,
                11.0,
                0.0,
                0.0,
                1.93,
                2.11,
                1.6,
                7.576234,
                21.4844,
                1.304473,
                128.0,
                0.0,
                -900.324578,
                -129.859807,
                -120.913351,
                -23.678437,
                -20.06763,
                -3.22309,
                -13.367803,
                -2.086602,
                -0.157407,
                -0.298706,
                0.0,
                0.0,
                0.0,
                0.0,
                0.0,
                0.0,
                0.0,
                0.0,
                0.0
            ],
            [
                79.0,
                6.0,
                11.0,
                0.0,
                0.0,
                2.54,
                2.14,
                1.35,
                9.225554,
                20.203,
                2.30861025,
                124.0,
                0.0,
                -2683.508245,
                -447.888973,
                -430.725701,
                -104.824516,
                -96.707,
                -22.078357,
                -81.511751,
                -18.578652,
                -3.113936,
                -12.131815,
                -2.002495,
                -0.162334,
                -3.486824,
                -0.304738,
                0.0,
                0.0,
                0.0,
                0.0,
                0.0
            ],
            [
                79.0,
                6.0,
                11.0,
                0.0,
                0.0,
                2.54,
                2.14,
                1.35,
                9.225554,
                20.203,
                2.30861025,
                124.0,
                0.0,
                -2683.508245,
                -447.888973,
                -430.725701,
                -104.824516,
                -96.707,
                -22.078357,
                -81.511751,
                -18.578652,
                -3.113936,
                -12.131815,
                -2.002495,
                -0.162334,
                -3.486824,
                -0.304738,
                0.0,
                0.0,
                0.0,
                0.0,
                0.0
            ],
            [
                8.0,
                2.0,
                16.0,
                0.0,
                0.0,
                3.44,
                1.52,
                0.6,
                13.618055,
                35.12112,
                1.4611053,
                63.0,
                0.0,
                -18.758245,
                -0.871362,
                -0.338381,
                0.0,
                0.0,
                0.0,
                0.0,
                0.0,
                0.0,
                0.0,
                0.0,
                0.0,
                0.0,
                0.0,
                0.0,
                0.0,
                0.0,
                0.0,
                0.0
            ],
            [
                8.0,
                2.0,
                16.0,
                0.0,
                0.0,
                3.44,
                1.52,
                0.6,
                13.618055,
                35.12112,
                1.4611053,
                63.0,
                1.0,
                -18.758245,
                -0.871362,
                -0.338381,
                0.0,
                0.0,
                0.0,
                0.0,
                0.0,
                0.0,
                0.0,
                0.0,
                0.0,
                0.0,
                0.0,
                0.0,
                0.0,
                0.0,
                0.0,
                0.0
            ],
            [
                8.0,
                2.0,
                16.0,
                0.0,
                0.0,
                3.44,
                1.52,
                0.6,
                13.618055,
                35.12112,
                1.4611053,
                63.0,
                0.0,
                -18.758245,
                -0.871362,
                -0.338381,
                0.0,
                0.0,
                0.0,
                0.0,
                0.0,
                0.0,
                0.0,
                0.0,
                0.0,
                0.0,
                0.0,
                0.0,
                0.0,
                0.0,
                0.0,
                0.0
            ],
            [
                8.0,
                2.0,
                16.0,
                0.0,
                0.0,
                3.44,
                1.52,
                0.6,
                13.618055,
                35.12112,
                1.4611053,
                63.0,
                0.0,
                -18.758245,
                -0.871362,
                -0.338381,
                0.0,
                0.0,
                0.0,
                0.0,
                0.0,
                0.0,
                0.0,
                0.0,
                0.0,
                0.0,
                0.0,
                0.0,
                0.0,
                0.0,
                0.0,
                0.0
            ]
        ],
        "edges": [
            [
                0,
                6
            ],
            [
                0,
                4
            ],
            [
                1,
                7
            ],
            [
                1,
                5
            ],
            [
                2,
                4
            ],
            [
                2,
                7
            ],
            [
                2,
                5
            ],
            [
                2,
                6
            ],
            [
                3,
                7
            ],
            [
                3,
                6
            ],
            [
                3,
                4
            ],
            [
                3,
                5
            ],
            [
                4,
                3
            ],
            [
                4,
                2
            ],
            [
                4,
                0
            ],
            [
                5,
                1
            ],
            [
                5,
                2
            ],
            [
                5,
                3
            ],
            [
                6,
                3
            ],
            [
                6,
                0
            ],
            [
                6,
                2
            ],
            [
                7,
                3
            ],
            [
                7,
                2
            ],
            [
                7,
                1
            ]
        ],
        "edge_attr": [
            [
                2.112389096960098,
                0
            ],
            [
                2.112389096960098,
                0
            ],
            [
                2.1123890969600985,
                0
            ],
            [
                2.1123890969600985,
                1
            ],
            [
                2.0041051963278567,
                0
            ],
            [
                2.0067254438278246,
                0
            ],
            [
                2.006725443827824,
                1
            ],
            [
                2.0041051963278567,
                0
            ],
            [
                2.004105196327856,
                0
            ],
            [
                2.0067254438278246,
                0
            ],
            [
                2.0067254438278246,
                0
            ],
            [
                2.0041051963278567,
                1
            ],
            [
                2.0067254438278246,
                0
            ],
            [
                2.0041051963278567,
                0
            ],
            [
                2.112389096960098,
                0
            ],
            [
                2.1123890969600985,
                1
            ],
            [
                2.006725443827824,
                1
            ],
            [
                2.0041051963278567,
                1
            ],
            [
                2.0067254438278246,
                0
            ],
            [
                2.112389096960098,
                0
            ],
            [
                2.0041051963278567,
                0
            ],
            [
                2.004105196327856,
                0
            ],
            [
                2.0067254438278246,
                0
            ],
            [
                2.1123890969600985,
                0
            ]
        ]
    },
    {
        "crystal_index": 5,
        "crystal_name": "AgAuO2",
        "Oxy_site_label": "O1",
        "Oxy_site_index": 6,
        "Oxy_vacancy_formation_energy": 2.31297225999999,
        "node_features": [
            [
                47.0,
                5.0,
                11.0,
                0.0,
                0.0,
                1.93,
                2.11,
                1.6,
                7.576234,
                21.4844,
                1.304473,
                128.0,
                0.0,
                -900.324578,
                -129.859807,
                -120.913351,
                -23.678437,
                -20.06763,
                -3.22309,
                -13.367803,
                -2.086602,
                -0.157407,
                -0.298706,
                0.0,
                0.0,
                0.0,
                0.0,
                0.0,
                0.0,
                0.0,
                0.0,
                0.0
            ],
            [
                47.0,
                5.0,
                11.0,
                0.0,
                0.0,
                1.93,
                2.11,
                1.6,
                7.576234,
                21.4844,
                1.304473,
                128.0,
                0.0,
                -900.324578,
                -129.859807,
                -120.913351,
                -23.678437,
                -20.06763,
                -3.22309,
                -13.367803,
                -2.086602,
                -0.157407,
                -0.298706,
                0.0,
                0.0,
                0.0,
                0.0,
                0.0,
                0.0,
                0.0,
                0.0,
                0.0
            ],
            [
                79.0,
                6.0,
                11.0,
                0.0,
                0.0,
                2.54,
                2.14,
                1.35,
                9.225554,
                20.203,
                2.30861025,
                124.0,
                0.0,
                -2683.508245,
                -447.888973,
                -430.725701,
                -104.824516,
                -96.707,
                -22.078357,
                -81.511751,
                -18.578652,
                -3.113936,
                -12.131815,
                -2.002495,
                -0.162334,
                -3.486824,
                -0.304738,
                0.0,
                0.0,
                0.0,
                0.0,
                0.0
            ],
            [
                79.0,
                6.0,
                11.0,
                0.0,
                0.0,
                2.54,
                2.14,
                1.35,
                9.225554,
                20.203,
                2.30861025,
                124.0,
                0.0,
                -2683.508245,
                -447.888973,
                -430.725701,
                -104.824516,
                -96.707,
                -22.078357,
                -81.511751,
                -18.578652,
                -3.113936,
                -12.131815,
                -2.002495,
                -0.162334,
                -3.486824,
                -0.304738,
                0.0,
                0.0,
                0.0,
                0.0,
                0.0
            ],
            [
                8.0,
                2.0,
                16.0,
                0.0,
                0.0,
                3.44,
                1.52,
                0.6,
                13.618055,
                35.12112,
                1.4611053,
                63.0,
                0.0,
                -18.758245,
                -0.871362,
                -0.338381,
                0.0,
                0.0,
                0.0,
                0.0,
                0.0,
                0.0,
                0.0,
                0.0,
                0.0,
                0.0,
                0.0,
                0.0,
                0.0,
                0.0,
                0.0,
                0.0
            ],
            [
                8.0,
                2.0,
                16.0,
                0.0,
                0.0,
                3.44,
                1.52,
                0.6,
                13.618055,
                35.12112,
                1.4611053,
                63.0,
                0.0,
                -18.758245,
                -0.871362,
                -0.338381,
                0.0,
                0.0,
                0.0,
                0.0,
                0.0,
                0.0,
                0.0,
                0.0,
                0.0,
                0.0,
                0.0,
                0.0,
                0.0,
                0.0,
                0.0,
                0.0
            ],
            [
                8.0,
                2.0,
                16.0,
                0.0,
                0.0,
                3.44,
                1.52,
                0.6,
                13.618055,
                35.12112,
                1.4611053,
                63.0,
                1.0,
                -18.758245,
                -0.871362,
                -0.338381,
                0.0,
                0.0,
                0.0,
                0.0,
                0.0,
                0.0,
                0.0,
                0.0,
                0.0,
                0.0,
                0.0,
                0.0,
                0.0,
                0.0,
                0.0,
                0.0
            ],
            [
                8.0,
                2.0,
                16.0,
                0.0,
                0.0,
                3.44,
                1.52,
                0.6,
                13.618055,
                35.12112,
                1.4611053,
                63.0,
                0.0,
                -18.758245,
                -0.871362,
                -0.338381,
                0.0,
                0.0,
                0.0,
                0.0,
                0.0,
                0.0,
                0.0,
                0.0,
                0.0,
                0.0,
                0.0,
                0.0,
                0.0,
                0.0,
                0.0,
                0.0
            ]
        ],
        "edges": [
            [
                0,
                6
            ],
            [
                0,
                4
            ],
            [
                1,
                7
            ],
            [
                1,
                5
            ],
            [
                2,
                4
            ],
            [
                2,
                7
            ],
            [
                2,
                5
            ],
            [
                2,
                6
            ],
            [
                3,
                7
            ],
            [
                3,
                6
            ],
            [
                3,
                4
            ],
            [
                3,
                5
            ],
            [
                4,
                3
            ],
            [
                4,
                2
            ],
            [
                4,
                0
            ],
            [
                5,
                1
            ],
            [
                5,
                2
            ],
            [
                5,
                3
            ],
            [
                6,
                3
            ],
            [
                6,
                0
            ],
            [
                6,
                2
            ],
            [
                7,
                3
            ],
            [
                7,
                2
            ],
            [
                7,
                1
            ]
        ],
        "edge_attr": [
            [
                2.112389096960098,
                1
            ],
            [
                2.112389096960098,
                0
            ],
            [
                2.1123890969600985,
                0
            ],
            [
                2.1123890969600985,
                0
            ],
            [
                2.0041051963278567,
                0
            ],
            [
                2.0067254438278246,
                0
            ],
            [
                2.006725443827824,
                0
            ],
            [
                2.0041051963278567,
                1
            ],
            [
                2.004105196327856,
                0
            ],
            [
                2.0067254438278246,
                1
            ],
            [
                2.0067254438278246,
                0
            ],
            [
                2.0041051963278567,
                0
            ],
            [
                2.0067254438278246,
                0
            ],
            [
                2.0041051963278567,
                0
            ],
            [
                2.112389096960098,
                0
            ],
            [
                2.1123890969600985,
                0
            ],
            [
                2.006725443827824,
                0
            ],
            [
                2.0041051963278567,
                0
            ],
            [
                2.0067254438278246,
                1
            ],
            [
                2.112389096960098,
                1
            ],
            [
                2.0041051963278567,
                1
            ],
            [
                2.004105196327856,
                0
            ],
            [
                2.0067254438278246,
                0
            ],
            [
                2.1123890969600985,
                0
            ]
        ]
    },
    {
        "crystal_index": 5,
        "crystal_name": "AgAuO2",
        "Oxy_site_label": "O1",
        "Oxy_site_index": 7,
        "Oxy_vacancy_formation_energy": 2.31297225999999,
        "node_features": [
            [
                47.0,
                5.0,
                11.0,
                0.0,
                0.0,
                1.93,
                2.11,
                1.6,
                7.576234,
                21.4844,
                1.304473,
                128.0,
                0.0,
                -900.324578,
                -129.859807,
                -120.913351,
                -23.678437,
                -20.06763,
                -3.22309,
                -13.367803,
                -2.086602,
                -0.157407,
                -0.298706,
                0.0,
                0.0,
                0.0,
                0.0,
                0.0,
                0.0,
                0.0,
                0.0,
                0.0
            ],
            [
                47.0,
                5.0,
                11.0,
                0.0,
                0.0,
                1.93,
                2.11,
                1.6,
                7.576234,
                21.4844,
                1.304473,
                128.0,
                0.0,
                -900.324578,
                -129.859807,
                -120.913351,
                -23.678437,
                -20.06763,
                -3.22309,
                -13.367803,
                -2.086602,
                -0.157407,
                -0.298706,
                0.0,
                0.0,
                0.0,
                0.0,
                0.0,
                0.0,
                0.0,
                0.0,
                0.0
            ],
            [
                79.0,
                6.0,
                11.0,
                0.0,
                0.0,
                2.54,
                2.14,
                1.35,
                9.225554,
                20.203,
                2.30861025,
                124.0,
                0.0,
                -2683.508245,
                -447.888973,
                -430.725701,
                -104.824516,
                -96.707,
                -22.078357,
                -81.511751,
                -18.578652,
                -3.113936,
                -12.131815,
                -2.002495,
                -0.162334,
                -3.486824,
                -0.304738,
                0.0,
                0.0,
                0.0,
                0.0,
                0.0
            ],
            [
                79.0,
                6.0,
                11.0,
                0.0,
                0.0,
                2.54,
                2.14,
                1.35,
                9.225554,
                20.203,
                2.30861025,
                124.0,
                0.0,
                -2683.508245,
                -447.888973,
                -430.725701,
                -104.824516,
                -96.707,
                -22.078357,
                -81.511751,
                -18.578652,
                -3.113936,
                -12.131815,
                -2.002495,
                -0.162334,
                -3.486824,
                -0.304738,
                0.0,
                0.0,
                0.0,
                0.0,
                0.0
            ],
            [
                8.0,
                2.0,
                16.0,
                0.0,
                0.0,
                3.44,
                1.52,
                0.6,
                13.618055,
                35.12112,
                1.4611053,
                63.0,
                0.0,
                -18.758245,
                -0.871362,
                -0.338381,
                0.0,
                0.0,
                0.0,
                0.0,
                0.0,
                0.0,
                0.0,
                0.0,
                0.0,
                0.0,
                0.0,
                0.0,
                0.0,
                0.0,
                0.0,
                0.0
            ],
            [
                8.0,
                2.0,
                16.0,
                0.0,
                0.0,
                3.44,
                1.52,
                0.6,
                13.618055,
                35.12112,
                1.4611053,
                63.0,
                0.0,
                -18.758245,
                -0.871362,
                -0.338381,
                0.0,
                0.0,
                0.0,
                0.0,
                0.0,
                0.0,
                0.0,
                0.0,
                0.0,
                0.0,
                0.0,
                0.0,
                0.0,
                0.0,
                0.0,
                0.0
            ],
            [
                8.0,
                2.0,
                16.0,
                0.0,
                0.0,
                3.44,
                1.52,
                0.6,
                13.618055,
                35.12112,
                1.4611053,
                63.0,
                0.0,
                -18.758245,
                -0.871362,
                -0.338381,
                0.0,
                0.0,
                0.0,
                0.0,
                0.0,
                0.0,
                0.0,
                0.0,
                0.0,
                0.0,
                0.0,
                0.0,
                0.0,
                0.0,
                0.0,
                0.0
            ],
            [
                8.0,
                2.0,
                16.0,
                0.0,
                0.0,
                3.44,
                1.52,
                0.6,
                13.618055,
                35.12112,
                1.4611053,
                63.0,
                1.0,
                -18.758245,
                -0.871362,
                -0.338381,
                0.0,
                0.0,
                0.0,
                0.0,
                0.0,
                0.0,
                0.0,
                0.0,
                0.0,
                0.0,
                0.0,
                0.0,
                0.0,
                0.0,
                0.0,
                0.0
            ]
        ],
        "edges": [
            [
                0,
                6
            ],
            [
                0,
                4
            ],
            [
                1,
                7
            ],
            [
                1,
                5
            ],
            [
                2,
                4
            ],
            [
                2,
                7
            ],
            [
                2,
                5
            ],
            [
                2,
                6
            ],
            [
                3,
                7
            ],
            [
                3,
                6
            ],
            [
                3,
                4
            ],
            [
                3,
                5
            ],
            [
                4,
                3
            ],
            [
                4,
                2
            ],
            [
                4,
                0
            ],
            [
                5,
                1
            ],
            [
                5,
                2
            ],
            [
                5,
                3
            ],
            [
                6,
                3
            ],
            [
                6,
                0
            ],
            [
                6,
                2
            ],
            [
                7,
                3
            ],
            [
                7,
                2
            ],
            [
                7,
                1
            ]
        ],
        "edge_attr": [
            [
                2.112389096960098,
                0
            ],
            [
                2.112389096960098,
                0
            ],
            [
                2.1123890969600985,
                1
            ],
            [
                2.1123890969600985,
                0
            ],
            [
                2.0041051963278567,
                0
            ],
            [
                2.0067254438278246,
                1
            ],
            [
                2.006725443827824,
                0
            ],
            [
                2.0041051963278567,
                0
            ],
            [
                2.004105196327856,
                1
            ],
            [
                2.0067254438278246,
                0
            ],
            [
                2.0067254438278246,
                0
            ],
            [
                2.0041051963278567,
                0
            ],
            [
                2.0067254438278246,
                0
            ],
            [
                2.0041051963278567,
                0
            ],
            [
                2.112389096960098,
                0
            ],
            [
                2.1123890969600985,
                0
            ],
            [
                2.006725443827824,
                0
            ],
            [
                2.0041051963278567,
                0
            ],
            [
                2.0067254438278246,
                0
            ],
            [
                2.112389096960098,
                0
            ],
            [
                2.0041051963278567,
                0
            ],
            [
                2.004105196327856,
                1
            ],
            [
                2.0067254438278246,
                1
            ],
            [
                2.1123890969600985,
                1
            ]
        ]
    }
]